crime_news_classifer_spanish/.DS_Store
crime_news_classifer_spanish/__init__.py
crime_news_classifer_spanish/crime_classifier.py
crime_news_classifer_spanish/test_crime_classifier.py
crime_news_classifer_spanish/__pycache__/cleaner.cpython-37.pyc
crime_news_classifer_spanish/__pycache__/sentiment_analysis.cpython-37.pyc
crime_news_classifer_spanish/saved_model/.DS_Store
crime_news_classifer_spanish/saved_model/model.h5
crime_news_classifer_spanish/saved_model/model.json
crime_news_classifer_spanish/saved_model/tokenizer.pickle
crime_news_classifer_spanish-0.0.2.dist-info/LICENSE
crime_news_classifer_spanish-0.0.2.dist-info/METADATA
crime_news_classifer_spanish-0.0.2.dist-info/WHEEL
crime_news_classifer_spanish-0.0.2.dist-info/top_level.txt
crime_news_classifer_spanish-0.0.2.dist-info/RECORD
