Metadata-Version: 2.1
Name: crime-news-classifer-spanish
Version: 0.0.2
Summary: A classifier for crime and violence newspaper news in spanish
Home-page: https://github.com/news-scrapers/crime-in-news-classifier
Author: Hugo J. Bello
Author-email: hjbello.wk@gmail.com
License: UNKNOWN
Platform: UNKNOWN
Classifier: Programming Language :: Python :: 3
Classifier: License :: OSI Approved :: MIT License
Classifier: Operating System :: OS Independent
